Metadata-Version: 2.1
Name: MyFirstModuleskwdfewfsd
Version: 0.0.2
Summary: Very short desc
Home-page: UNKNOWN
Author: CookiesKush420
Author-email: cookies@mail.com
License: MIT
Keywords: calculator
Platform: UNKNOWN
Classifier: Development Status :: 4 - Beta
Classifier: Intended Audience :: Developers
Classifier: License :: OSI Approved :: MIT License
Classifier: Programming Language :: Python :: 3
License-File: LICENCE.txt
